nasawrapper/__init__.py
nasawrapper/apod.py
nasawrapper/errors.py
nasawrapper/neows.py
nasawrapper/utils/__init__.py
nasawrapper/utils/get_remaining_rate_limit.py
nasawrapper-0.3.2.dist-info/LICENSE
nasawrapper-0.3.2.dist-info/METADATA
nasawrapper-0.3.2.dist-info/WHEEL
nasawrapper-0.3.2.dist-info/top_level.txt
nasawrapper-0.3.2.dist-info/RECORD
